XStatic_moment-2.8.4.3-nspkg.pth
XStatic_moment-2.8.4.3.dist-info/DESCRIPTION.rst
XStatic_moment-2.8.4.3.dist-info/METADATA
XStatic_moment-2.8.4.3.dist-info/RECORD
XStatic_moment-2.8.4.3.dist-info/WHEEL
XStatic_moment-2.8.4.3.dist-info/metadata.json
XStatic_moment-2.8.4.3.dist-info/namespace_packages.txt
XStatic_moment-2.8.4.3.dist-info/top_level.txt
xstatic/pkg/moment/__init__.py
xstatic/pkg/moment/data/moment-with-locales.min.js
xstatic/pkg/moment/data/moment.min.js
