Metadata-Version: 2.0
Name: XStatic-moment
Version: 2.8.4.3
Summary: moment 2.8.4 (XStatic packaging standard)
Home-page: https://github.com/moment/moment
Maintainer: Michal Arbet
Maintainer-email: michal.arbet@ultimum.io
License: (same as moment)
Keywords: moment xstatic
Platform: any
